pelican/plugins/bibliography/__init__.py
pelican/plugins/bibliography/bibliography.py
pelican/plugins/bibliography/data/templates/bibentry.html
pelican/plugins/bibliography/data/templates/bibliography.html
pelican/plugins/bibliography/data/templates/citation.html
pelican/plugins/bibliography/test_bibliography.py
pelican_bibliography-0.5.2.dist-info/LICENSE
pelican_bibliography-0.5.2.dist-info/WHEEL
pelican_bibliography-0.5.2.dist-info/METADATA
pelican_bibliography-0.5.2.dist-info/RECORD
