Metadata-Version: 2.1
Name: pelican-bibliography
Version: 0.5.2
Summary: Generated bibliography in Pelican that can be rendered in references and citations
Home-page: https://github.com/micahjsmith/pelican-bibliography
License: MIT
Keywords: pelican,plugin,bibtex
Author: Micah Smith
Author-email: micahjsmith@gmail.com
Requires-Python: >=3.6,<4.0
Classifier: Development Status :: 2 - Pre-Alpha
Classifier: Environment :: Console
Classifier: Framework :: Pelican
Classifier: Framework :: Pelican :: Plugins
Classifier: Intended Audience :: End Users/Desktop
Classifier: License :: OSI Approved :: MIT License
Classifier: Operating System :: OS Independent
Classifier: Programming Language :: Python :: 3
Classifier: Programming Language :: Python :: 3.10
Classifier: Programming Language :: Python :: 3.6
Classifier: Programming Language :: Python :: 3.7
Classifier: Programming Language :: Python :: 3.8
Classifier: Programming Language :: Python :: 3.9
Classifier: Topic :: Internet :: WWW/HTTP
Classifier: Topic :: Software Development :: Libraries :: Python Modules
Provides-Extra: markdown
Requires-Dist: citeproc-py (>=0.5.1,<0.6.0)
Requires-Dist: pelican (>=4.5,<5.0)
Requires-Dist: pybtex (>=0.23.0,<0.24.0)
Requires-Dist: pyyaml (>=5.3,<6.0)
Project-URL: Documentation, https://docs.getpelican.com
Project-URL: Funding, https://donate.getpelican.com/
Project-URL: Issue Tracker, https://github.com/micahjsmith/pelican-bibliography/issues
Project-URL: Repository, https://github.com/micahjsmith/pelican-bibliography
